Metadata-Version: 2.4
Name: ui-coverage-tool
Version: 0.32.0
Summary: UI Coverage Tool is an innovative, no-overhead solution for tracking and visualizing UI test coverage — directly on your actual application, not static snapshots.
Author-email: Nikita Filonov <filonov.nikitkaa@gmail.com>
Maintainer-email: Nikita Filonov <filonov.nikitkaa@gmail.com>
License:                                  Apache License
Project-URL: Homepage, https://github.com/Nikita-Filonov/ui-coverage-tool
Project-URL: Repository, https://github.com/Nikita-Filonov/ui-coverage-tool
Project-URL: Issues, https://github.com/Nikita-Filonov/ui-coverage-tool/issues
Keywords: python,coverage,ui-coverage,ui-testing,test-coverage,frontend-testing,visual-testing,automation,qa,quality-assurance,reporting,html-report,pytest,selenium,playwright,web-testing,test-analytics
Classifier: Programming Language :: Python :: 3
Classifier: Programming Language :: Python :: 3.11
Classifier: Programming Language :: Python :: 3.12
Classifier: License :: OSI Approved :: MIT License
Classifier: Operating System :: OS Independent
Classifier: Intended Audience :: Developers
Classifier: Topic :: Software Development :: Testing
Classifier: Topic :: Software Development :: Quality Assurance
Requires-Python: >=3.11
License-File: LICENSE
Requires-Dist: click==8.1.8
Requires-Dist: pyyaml==6.0.2
Requires-Dist: pydantic==2.11.3
Requires-Dist: pydantic-settings==2.8.1
Provides-Extra: test
Requires-Dist: pytest; extra == "test"
Requires-Dist: pytest-cov; extra == "test"
Dynamic: license-file
